setup.py
rulebox/__init__.py
rulebox/bbcode.py
rulebox/suitlons.py
rulebox/templating.py
rulebox.egg-info/PKG-INFO
rulebox.egg-info/SOURCES.txt
rulebox.egg-info/dependency_links.txt
rulebox.egg-info/not-zip-safe
rulebox.egg-info/requires.txt
rulebox.egg-info/top_level.txt