Metadata-Version: 1.0
Name: rulebox
Version: 1.1.1
Summary: A package containing various sets of rules for use with
Home-page: http://www.suitframework.com/
Author: Brandon Evans and Chris Santiago
Author-email: admin@brandonevans.org and faltzermaster@aol.com
License: LGPL
Keywords: suit template rules rulesets
Platform: UNKNOWN
